{
  "slug": "28-years-later-death-zombies-and-one-of-the-year-s-best-movi",
  "title": "'28 Years Later': Death, Zombies, and One of the Year's Best Movies",
  "show": "The Big Picture",
  "network": "The Ringer",
  "hosts": [
    "Sean Fennessey",
    "Amanda Dobbins",
    "Chris Ryan"
  ],
  "published": "2025-06-21",
  "runtimeMin": 83,
  "format": "Sean, Amanda, and Chris review '28 Years Later,' the Danny Boyle and Alex Garland reunion 23 years after '28 Days Later.' The news rundown covers the Springsteen and Bigelow trailers, the fall release-date pileup, and Tom Cruise's honorary Oscar.",
  "segments": [
    {
      "kind": "discussion",
      "heading": "The news rundown",
      "note": "trailers, casting, and release-date chess",
      "films": [
        {
          "title": "Springsteen: Deliver Me from Nowhere",
          "year": 2025,
          "note": "Scott Cooper's Springsteen film, Jeremy Allen White as Bruce recording 'Nebraska,' Jeremy Strong as Jon Landau. Out October 24; the hosts are wary of a tortured-artist treatment."
        },
        {
          "title": "A House of Dynamite",
          "year": 2025,
          "note": "Kathryn Bigelow's first film since 'Detroit,' scripted by Noah Oppenheim. A missile is launched at the U.S. and no one knows the source. Idris Elba, Rebecca Ferguson, Tracy Letts. Netflix, October 24."
        },
        {
          "title": "Die My Love",
          "year": 2025,
          "note": "Lynne Ramsay's Cannes title, Jennifer Lawrence as a mother with postpartum depression. Acquired for $24 million; moved to November 7."
        },
        {
          "title": "Sentimental Value",
          "year": 2025,
          "note": "Joachim Trier's Cannes film, also dated November 7."
        },
        {
          "title": "Materialists",
          "year": 2025,
          "note": "Celine Song's drama, marketed as a rom-com. The hosts note the trailer tricked audiences into theaters."
        },
        {
          "title": "The Running Man",
          "year": 2025,
          "note": "Edgar Wright's remake with Glen Powell, also November 7. Same core demo as 'Predator: Badlands.'"
        },
        {
          "title": "Predator: Badlands",
          "year": 2025,
          "note": "Dan Trachtenberg's next Predator, November 7; Sean caught an extended trailer before '28 Years Later.'"
        },
        {
          "title": "Predator: Killer of Killers",
          "year": 2025,
          "note": "The animated Predator anthology, which Chris happily watched as a completist."
        },
        {
          "title": "The Odyssey",
          "year": 2026,
          "note": "Christopher Nolan's next, rumored to have a teaser attached to 'Jurassic World Rebirth.'"
        },
        {
          "title": "Jurassic World Rebirth",
          "year": 2025,
          "note": "Sean bought an 8 a.m. opening-day ticket, partly to catch the rumored Odyssey teaser."
        }
      ]
    },
    {
      "kind": "review",
      "heading": "'28 Years Later'",
      "note": "one of the year's best",
      "films": [
        {
          "title": "28 Years Later",
          "year": 2025,
          "note": "Boyle and Garland reunite 23 years on. Shot on iPhone 15 Pro Max, scored by Young Fathers: a father-son hunting rite (Aaron Taylor-Johnson, newcomer Alfie Williams as Spike) that turns into coming-of-age folk horror. Ralph Fiennes as a bone-temple doctor, Jodie Comer as the dying mother. A fallen-empire Brexit allegory with plenty of gore, and all three hosts have it as a favorite of the year."
        },
        {
          "title": "28 Days Later",
          "year": 2002,
          "note": "The Boyle-Garland original, shot on low-res digital video. Amanda rewatched it alongside the sequel this week."
        },
        {
          "title": "28 Weeks Later",
          "year": 2007,
          "note": "The 2007 sequel, quietly retconned here: the new film says continental Europe contained the virus and moved on."
        }
      ]
    }
  ],
  "referenced": [
    {
      "group": "The Danny Boyle canon",
      "films": [
        "Trainspotting",
        "Shallow Grave",
        "Sunshine",
        "Steve Jobs",
        "T2 Trainspotting",
        "Trance",
        "127 Hours",
        "A Life Less Ordinary",
        "The Beach",
        "Yesterday"
      ]
    },
    {
      "group": "Garland's other films",
      "films": [
        "Annihilation",
        "Men",
        "Civil War",
        "Warfare"
      ]
    },
    {
      "group": "Visual and thematic touchstones",
      "films": [
        "Sorcerer",
        "The Lighthouse",
        "Henry V",
        "Kes",
        "Cannibal Holocaust",
        "Children of Men",
        "The Wizard of Oz",
        "War Horse",
        "Tangerine",
        "High Flying Bird",
        "Unsane"
      ]
    },
    {
      "group": "Elsewhere in 2025",
      "films": [
        "Sinners",
        "Black Bag",
        "Ballerina",
        "A Working Man",
        "The Amateur",
        "The Accountant 2",
        "The Marvels",
        "Candyman"
      ]
    },
    {
      "group": "In the news, in passing",
      "films": [
        "A Complete Unknown",
        "The Color of Money",
        "Backdraft",
        "A Beautiful Mind",
        "Apollo 13",
        "House at the End of the Street",
        "Silver Linings Playbook",
        "Die Hard with a Vengeance",
        "Jackie",
        "Marriage Story",
        "Detroit",
        "The Dark Knight",
        "Dunkirk"
      ]
    }
  ],
  "tmdbOverrides": {
    "The Accountant 2": 870028,
    "Candyman": 565028
  },
  "excluded": {
    "TV": [
      "Zero Day",
      "The Last of Us",
      "The Pit",
      "Adolescence",
      "Chad Powers",
      "Texas Chainsaw Massacre (TV adaptation)",
      "Shifty",
      "Bluey",
      "Teletubbies"
    ],
    "Video games": [
      "Elden Ring"
    ],
    "Podcasts": [
      "60 Songs That Explain the '90s"
    ],
    "Ads": [
      "Nordstrom Rack",
      "Red Bull Athlete Challenge"
    ]
  },
  "tmdb": {
    "Springsteen: Deliver Me from Nowhere": {
      "id": 1230368,
      "poster": "/csBV3eq4RDjNg1acNQ8kwOZyPlZ.jpg",
      "title": "Springsteen: Deliver Me from Nowhere",
      "year": 2025
    },
    "A House of Dynamite": {
      "id": 1290159,
      "poster": "/AiJ8L90ftPAwVf3SDx7Fj9IMZoy.jpg",
      "title": "A House of Dynamite",
      "year": 2025
    },
    "Die My Love": {
      "id": 1033148,
      "poster": "/kajpShbFhOdpl6yCrLezMrr9tB4.jpg",
      "title": "Die My Love",
      "year": 2025
    },
    "Sentimental Value": {
      "id": 1124566,
      "poster": "/pz9NCWxxOk3o0W3v1Zkhawrwb4i.jpg",
      "title": "Sentimental Value",
      "year": 2025
    },
    "Materialists": {
      "id": 1136867,
      "poster": "/eDo0pNruy0Qgj6BdTyHIR4cxHY8.jpg",
      "title": "Materialists",
      "year": 2025
    },
    "The Running Man": {
      "id": 798645,
      "poster": "/dKL78O9zxczVgjtNcQ9UkbYLzqX.jpg",
      "title": "The Running Man",
      "year": 2025
    },
    "Predator: Badlands": {
      "id": 1242898,
      "poster": "/pHpq9yNUIo6aDoCXEBzjSolywgz.jpg",
      "title": "Predator: Badlands",
      "year": 2025
    },
    "Predator: Killer of Killers": {
      "id": 1376434,
      "poster": "/2XDQa6EmFHSA37j1t0w88vpWqj9.jpg",
      "title": "Predator: Killer of Killers",
      "year": 2025
    },
    "The Odyssey": {
      "id": 1368337,
      "poster": "/5rhTDKUhPYvpdQIijFIs5VoWsON.jpg",
      "title": "The Odyssey",
      "year": 2026
    },
    "Jurassic World Rebirth": {
      "id": 1234821,
      "poster": "/1RICxzeoNCAO5NpcRMIgg1XT6fm.jpg",
      "title": "Jurassic World Rebirth",
      "year": 2025
    },
    "28 Years Later": {
      "id": 1100988,
      "poster": "/n5FygjEppOvac6yEaowi26nTyw3.jpg",
      "title": "28 Years Later",
      "year": 2025
    },
    "28 Days Later": {
      "id": 170,
      "poster": "/sQckQRt17VaWbo39GIu0TMOiszq.jpg",
      "title": "28 Days Later",
      "year": 2002
    },
    "28 Weeks Later": {
      "id": 1562,
      "poster": "/oix0aNv1lvW3nUGspUyvSIBlpbs.jpg",
      "title": "28 Weeks Later",
      "year": 2007
    },
    "Trainspotting": {
      "id": 627,
      "poster": "/1jUC02qsqS2NxBMFarbIhcQtazV.jpg",
      "title": "Trainspotting",
      "year": 1996
    },
    "Shallow Grave": {
      "id": 9905,
      "poster": "/gqvSKLbfIg1mja1ulVkVcLhdwWF.jpg",
      "title": "Shallow Grave",
      "year": 1994
    },
    "Sunshine": {
      "id": 1272,
      "poster": "/oKGGeJ8qvm0UmClz43VJ31fzPP7.jpg",
      "title": "Sunshine",
      "year": 2007
    },
    "Steve Jobs": {
      "id": 321697,
      "poster": "/ljiRO29Y9khEERRqMluptUYunJ9.jpg",
      "title": "Steve Jobs",
      "year": 2015
    },
    "T2 Trainspotting": {
      "id": 180863,
      "poster": "/xlbpCwa9OXXIiNgXcwuompHFIk9.jpg",
      "title": "T2 Trainspotting",
      "year": 2017
    },
    "Trance": {
      "id": 68727,
      "poster": "/3MVYuyVknNA9yC0Gy6z3zDAiWfX.jpg",
      "title": "Trance",
      "year": 2013
    },
    "127 Hours": {
      "id": 44115,
      "poster": "/h0RMdn0rfl9l5hWXz3tUh6QVkhi.jpg",
      "title": "127 Hours",
      "year": 2010
    },
    "A Life Less Ordinary": {
      "id": 8067,
      "poster": "/tk7WNEwLZepFU2yPIIkRuQOO0Q9.jpg",
      "title": "A Life Less Ordinary",
      "year": 1997
    },
    "The Beach": {
      "id": 1907,
      "poster": "/4y7LxD8TSi6AtsM2xSYqUm1gu7u.jpg",
      "title": "The Beach",
      "year": 2000
    },
    "Yesterday": {
      "id": 515195,
      "poster": "/9fYka5CQt9nrb6LOtKicysUf9NA.jpg",
      "title": "Yesterday",
      "year": 2019
    },
    "Annihilation": {
      "id": 300668,
      "poster": "/4YRplSk6BhH6PRuE9gfyw9byUJ6.jpg",
      "title": "Annihilation",
      "year": 2018
    },
    "Men": {
      "id": 780609,
      "poster": "/jo1Kv3P3UgDVk7JnUFr2Cl8WWUM.jpg",
      "title": "Men",
      "year": 2022
    },
    "Civil War": {
      "id": 929590,
      "poster": "/sh7Rg8Er3tFcN9BpKIPOMvALgZd.jpg",
      "title": "Civil War",
      "year": 2024
    },
    "Warfare": {
      "id": 1241436,
      "poster": "/l39TlELomwysfsr37vrvCV6rmaQ.jpg",
      "title": "Warfare",
      "year": 2025
    },
    "Sorcerer": {
      "id": 38985,
      "poster": "/2b7oexm173SF1FSEq0DdgxZZNRH.jpg",
      "title": "Sorcerer",
      "year": 1977
    },
    "The Lighthouse": {
      "id": 503919,
      "poster": "/yAKNmpcUweGH6WMCEWenwU9PsbE.jpg",
      "title": "The Lighthouse",
      "year": 2019
    },
    "Henry V": {
      "id": 22638,
      "poster": "/eAisr20DvaKJeHvjDN0oHSx0l7u.jpg",
      "title": "Henry V",
      "year": 1944
    },
    "Kes": {
      "id": 13384,
      "poster": "/r1FMq75irhsQBVGjXhPU4xA9SDo.jpg",
      "title": "Kes",
      "year": 1970
    },
    "Cannibal Holocaust": {
      "id": 8689,
      "poster": "/otxZzMh53TsN7yYFqSZ3rwH1yMd.jpg",
      "title": "Cannibal Holocaust",
      "year": 1980
    },
    "Children of Men": {
      "id": 9693,
      "poster": "/k9IAS4TehZFcKi4HVByxZNPfqex.jpg",
      "title": "Children of Men",
      "year": 2006
    },
    "The Wizard of Oz": {
      "id": 630,
      "poster": "/uCC3j4pV9eOZwzDUWp2ilbcTf1f.jpg",
      "title": "The Wizard of Oz",
      "year": 1939
    },
    "War Horse": {
      "id": 57212,
      "poster": "/3aRHhvvngFPJFy5uAjo7GVr3PhL.jpg",
      "title": "War Horse",
      "year": 2011
    },
    "Tangerine": {
      "id": 308084,
      "poster": "/EKLR5c61XQzBTeMokFrmS3kdt8.jpg",
      "title": "Tangerine",
      "year": 2015
    },
    "High Flying Bird": {
      "id": 510498,
      "poster": "/ccE21xixa1zhkGtWDr4n8ReOp40.jpg",
      "title": "High Flying Bird",
      "year": 2019
    },
    "Unsane": {
      "id": 467660,
      "poster": "/wdaUssQhZDOgegkJZx7NfY75HRX.jpg",
      "title": "Unsane",
      "year": 2018
    },
    "Sinners": {
      "id": 1233413,
      "poster": "/fWPgbnt2LSqkQ6cdQc0SZN9CpLm.jpg",
      "title": "Sinners",
      "year": 2025
    },
    "Black Bag": {
      "id": 1233575,
      "poster": "/hHPovtU4b96LHcoeEwRkGHI5btw.jpg",
      "title": "Black Bag",
      "year": 2025
    },
    "Ballerina": {
      "id": 541671,
      "poster": "/2VUmvqsHb6cEtdfscEA6fqqVzLg.jpg",
      "title": "Ballerina",
      "year": 2025
    },
    "A Working Man": {
      "id": 1197306,
      "poster": "/6FRFIogh3zFnVWn7Z6zcYnIbRcX.jpg",
      "title": "A Working Man",
      "year": 2025
    },
    "The Amateur": {
      "id": 1087891,
      "poster": "/SNEoUInCa5fAgwuEBMIMBGvkkh.jpg",
      "title": "The Amateur",
      "year": 2025
    },
    "The Accountant 2": {
      "id": 870028,
      "poster": "/lUvfTcOZiK0sdcX0WNLPbMyKjGm.jpg",
      "title": "The Accountant²",
      "year": 2025
    },
    "The Marvels": {
      "id": 609681,
      "poster": "/9GBhzXMFjgcZ3FdR9w3bUMMTps5.jpg",
      "title": "The Marvels",
      "year": 2023
    },
    "Candyman": {
      "id": 565028,
      "poster": "/dqoshZPLNsXlC1qtz5n34raUyrE.jpg",
      "title": "Candyman",
      "year": 2021
    },
    "A Complete Unknown": {
      "id": 661539,
      "poster": "/llWl3GtNoXosbvYboelmoT459NM.jpg",
      "title": "A Complete Unknown",
      "year": 2024
    },
    "The Color of Money": {
      "id": 11873,
      "poster": "/dVdnHmdQu3JtLAAksjTmTEF76gD.jpg",
      "title": "The Color of Money",
      "year": 1986
    },
    "Backdraft": {
      "id": 2924,
      "poster": "/bymJtYNIdiAiBR1LRetaJXbfryc.jpg",
      "title": "Backdraft",
      "year": 1991
    },
    "A Beautiful Mind": {
      "id": 453,
      "poster": "/rEIg5yJdNOt9fmX4P8gU9LeNoTQ.jpg",
      "title": "A Beautiful Mind",
      "year": 2001
    },
    "Apollo 13": {
      "id": 568,
      "poster": "/tVeKscCm2fY1xDXZk8PgnZ87h9S.jpg",
      "title": "Apollo 13",
      "year": 1995
    },
    "House at the End of the Street": {
      "id": 82505,
      "poster": "/A25qFUMXmVuDnuUCedkkYO1aKgU.jpg",
      "title": "House at the End of the Street",
      "year": 2012
    },
    "Silver Linings Playbook": {
      "id": 82693,
      "poster": "/fhHB1uvfFKKFbj6bTKE8xdtsjKi.jpg",
      "title": "Silver Linings Playbook",
      "year": 2012
    },
    "Die Hard with a Vengeance": {
      "id": 1572,
      "poster": "/buqmCdFQEWwEpL3agGgg2GVjN2d.jpg",
      "title": "Die Hard: With a Vengeance",
      "year": 1995
    },
    "Jackie": {
      "id": 376866,
      "poster": "/nF9N33PfhizMEzbfxHoxXBo2vx9.jpg",
      "title": "Jackie",
      "year": 2016
    },
    "Marriage Story": {
      "id": 492188,
      "poster": "/2JRyCKaRKyJAVpsIHeLvPw5nHmw.jpg",
      "title": "Marriage Story",
      "year": 2019
    },
    "Detroit": {
      "id": 407448,
      "poster": "/r0ldqSFASpqSM5xTrpcZGO6Ef2G.jpg",
      "title": "Detroit",
      "year": 2017
    },
    "The Dark Knight": {
      "id": 155,
      "poster": "/qJ2tW6WMUDux911r6m7haRef0WH.jpg",
      "title": "The Dark Knight",
      "year": 2008
    },
    "Dunkirk": {
      "id": 374720,
      "poster": "/b4Oe15CGLL61Ped0RAS9JpqdmCt.jpg",
      "title": "Dunkirk",
      "year": 2017
    }
  },
  "spotifyEpisodeId": "5BrXJS6mYb1O2IzoWRK8Xs"
}